README.md
setup.py
more_selenium/__init__.py
more_selenium/audio_recognition.py
more_selenium/check_version.py
more_selenium/sel_utils.py
more_selenium.egg-info/PKG-INFO
more_selenium.egg-info/SOURCES.txt
more_selenium.egg-info/dependency_links.txt
more_selenium.egg-info/requires.txt
more_selenium.egg-info/top_level.txt
more_selenium/audio_processing/ffmpeg.exe
more_selenium/google_authenticator/__init__.py
more_selenium/google_authenticator/secret_gen.py
more_selenium/google_authenticator/generated_python/__init__.py
more_selenium/google_authenticator/generated_python/google_auth_pb2.py