Metadata-Version: 2.1
Name: more-selenium
Version: 1.24
Summary: Better functionality for selenium
Home-page: https://github.com/MasterGrand/selenium_utils
Author: Max
Author-email: max@max.max
License: UNKNOWN
Platform: UNKNOWN
Classifier: Programming Language :: Python :: 3
Requires-Python: >2.7, <4
